[
  {
    "text": "Arcane Eye - 4th level Divination 🔮",
    "unique": false,
    "used": []
  },
  {
    "text": "Aura of Life - 4th level Abjuration 🛡️",
    "unique": false,
    "used": []
  },
  {
    "text": "Aura of Purity - 4th level Abjuration 🛡️",
    "unique": false,
    "used": []
  },
  {
    "text": "Banishment - 4th level Abjuration 🛡️",
    "unique": false,
    "used": []
  },
  {
    "text": "Blight - 4th level Necromancy 💀",
    "unique": false,
    "used": []
  },
  {
    "text": "Charm Monster - 4th level Enchantment 🤯",
    "unique": false,
    "used": []
  },
  {
    "text": "Compulsion - 4th level Enchantment 🤯",
    "unique": false,
    "used": []
  },
  {
    "text": "Confusion - 4th level Enchantment 🤯",
    "unique": false,
    "used": []
  },
  {
    "text": "Conjure Minor Elementals - 4th level Conjuration 📦",
    "unique": false,
    "used": []
  },
  {
    "text": "Conjure Woodland Beings - 4th level Conjuration 📦",
    "unique": false,
    "used": []
  },
  {
    "text": "Control Water - 4th level Transmutation ⚗️",
    "unique": false,
    "used": []
  },
  {
    "text": "Death Ward - 4th level Abjuration 🛡️",
    "unique": false,
    "used": []
  },
  {
    "text": "Dimension Door - 4th level Conjuration 📦",
    "unique": false,
    "used": []
  },
  {
    "text": "Dire Warning - 4th level Divination 🔮",
    "unique": false,
    "used": []
  },
  {
    "text": "Divination - 4th level Divination 🔮",
    "unique": false,
    "used": []
  },
  {
    "text": "Dominate Beast - 4th level Enchantment 🤯",
    "unique": false,
    "used": []
  },
  {
    "text": "Drayfn's Curse of Incompetence - 4th level Necromancy 💀",
    "unique": false,
    "used": []
  },
  {
    "text": "Elemental Bane - 4th level Transmutation ⚗️",
    "unique": false,
    "used": []
  },
  {
    "text": "Evard's Black Tentacles - 4th level Conjuration 📦",
    "unique": false,
    "used": []
  },
  {
    "text": "Fabricate - 4th level Transmutation ⚗️",
    "unique": false,
    "used": []
  },
  {
    "text": "Find Greater Steed - 4th level Conjuration 📦",
    "unique": false,
    "used": []
  },
  {
    "text": "Fire Dance - 4th level Illusion 🥸",
    "unique": false,
    "used": []
  },
  {
    "text": "Fire Shield - 4th level Evocation 💥",
    "unique": false,
    "used": []
  },
  {
    "text": "Fount of Moonlight - 4th level Evocation 💥",
    "unique": false,
    "used": []
  },
  {
    "text": "Freedom of Movement - 4th level Abjuration 🛡️",
    "unique": false,
    "used": []
  },
  {
    "text": "Gate Seal - 4th level Abjuration 🛡️",
    "unique": false,
    "used": []
  },
  {
    "text": "Giant Insect - 4th level Conjuration 📦",
    "unique": false,
    "used": []
  },
  {
    "text": "Grasping Vine - 4th level Conjuration 📦",
    "unique": false,
    "used": []
  },
  {
    "text": "Greater Invisibility - 4th level Illusion 🥸",
    "unique": false,
    "used": []
  },
  {
    "text": "Guardian of Faith - 4th level Conjuration 📦",
    "unique": false,
    "used": []
  },
  {
    "text": "Guardian of Nature - 4th level Transmutation ⚗️",
    "unique": false,
    "used": []
  },
  {
    "text": "Hallucinatory Terrain - 4th level Illusion 🥸",
    "unique": false,
    "used": []
  },
  {
    "text": "Ice Storm - 4th level Evocation 💥",
    "unique": false,
    "used": []
  },
  {
    "text": "Knife of Fate - 4th level Necromancy 💀",
    "unique": false,
    "used": []
  },
  {
    "text": "Leomund's Secret Chest - 4th level Conjuration 📦",
    "unique": false,
    "used": []
  },
  {
    "text": "Locate Creature - 4th level Divination 🔮",
    "unique": false,
    "used": []
  },
  {
    "text": "Lunar Transfer - 4th level Conjuration 📦",
    "unique": false,
    "used": []
  },
  {
    "text": "Mandy's Feral Follower - 4th level Transmutation ⚗️",
    "unique": false,
    "used": []
  },
  {
    "text": "Moonlight Sending - 4th level Conjuration 📦",
    "unique": false,
    "used": []
  },
  {
    "text": "Mordenkainen's Faithful Hound - 4th level Conjuration 📦",
    "unique": false,
    "used": []
  },
  {
    "text": "Mordenkainen's Private Sanctum - 4th level Abjuration 🛡️",
    "unique": false,
    "used": []
  },
  {
    "text": "Otiluke's Resilient Sphere - 4th level Abjuration 🛡️",
    "unique": false,
    "used": []
  },
  {
    "text": "Pacify Monster - 4th level Enchantment 🤯",
    "unique": false,
    "used": []
  },
  {
    "text": "Phantasmal Killer - 4th level Illusion 🥸",
    "unique": false,
    "used": []
  },
  {
    "text": "Polychromatic Bubble - 4th level Conjuration 📦",
    "unique": false,
    "used": []
  },
  {
    "text": "Polymorph - 4th level Transmutation ⚗️",
    "unique": false,
    "used": []
  },
  {
    "text": "Portho's Portal - 4th level Conjuration 📦",
    "unique": false,
    "used": []
  },
  {
    "text": "Raulothim's Psychic Lance - 4th level Enchantment 🤯",
    "unique": false,
    "used": []
  },
  {
    "text": "Ride the Lightning - 4th level Conjuration 📦",
    "unique": false,
    "used": []
  },
  {
    "text": "Searing Sun - 4th level Transmutation ⚗️",
    "unique": false,
    "used": []
  },
  {
    "text": "Shadow of Moil - 4th level Necromancy 💀",
    "unique": false,
    "used": []
  },
  {
    "text": "Shadow Step - 4th level Conjuration 📦",
    "unique": false,
    "used": []
  },
  {
    "text": "Shape Plants - 4th level Transmutation ⚗️",
    "unique": false,
    "used": []
  },
  {
    "text": "Sickening Radiance - 4th level Evocation 💥",
    "unique": false,
    "used": []
  },
  {
    "text": "Spider Song - 4th level Conjuration 📦",
    "unique": false,
    "used": []
  },
  {
    "text": "Spirit of Death - 4th level Necromancy 💀",
    "unique": false,
    "used": []
  },
  {
    "text": "Staggering Smite - 4th level Enchantment 🤯",
    "unique": false,
    "used": []
  },
  {
    "text": "Stellar Bodies - 4th level Evocation 💥",
    "unique": false,
    "used": []
  },
  {
    "text": "Stone Shape - 4th level Transmutation ⚗️",
    "unique": false,
    "used": []
  },
  {
    "text": "Stoneskin - 4th level Transmutation ⚗️",
    "unique": false,
    "used": []
  },
  {
    "text": "Storm Door - 4th level Conjuration 📦",
    "unique": false,
    "used": []
  },
  {
    "text": "Storm Sphere - 4th level Evocation 💥",
    "unique": false,
    "used": []
  },
  {
    "text": "Storm Stallion - 4th level Evocation 💥",
    "unique": false,
    "used": []
  },
  {
    "text": "Summon Aberration - 4th level Conjuration 📦",
    "unique": false,
    "used": []
  },
  {
    "text": "Summon Construct - 4th level Conjuration 📦",
    "unique": false,
    "used": []
  },
  {
    "text": "Summon Elemental - 4th level Conjuration 📦",
    "unique": false,
    "used": []
  },
  {
    "text": "Summon Greater Demon - 4th level Conjuration 📦",
    "unique": false,
    "used": []
  },
  {
    "text": "Supernal Smite - 4th level Evocation 💥",
    "unique": false,
    "used": []
  },
  {
    "text": "Vitriolic Sphere - 4th level Evocation 💥",
    "unique": false,
    "used": []
  },
  {
    "text": "Wall of Fire - 4th level Evocation 💥",
    "unique": false,
    "used": []
  },
  {
    "text": "Watery Sphere - 4th level Conjuration 📦",
    "unique": false,
    "used": []
  }
]