[
  {
    "text": "Amulet of dinosaur feathers (Sun Empire)",
    "unique": false,
    "used": []
  },
  {
    "text": "Bejeweled gold bracelet",
    "unique": false,
    "used": []
  },
  {
    "text": "Bejeweled ivory drinking horn with gold filigree",
    "unique": false,
    "used": []
  },
  {
    "text": "Bejeweled ivory drinking horn with gold inlay (Brazen Coalition)",
    "unique": false,
    "used": []
  },
  {
    "text": "Black velvet mask stitched with silver thread",
    "unique": false,
    "used": []
  },
  {
    "text": "Bottle stopper cork embossed with gold leaf and set with amethysts",
    "unique": false,
    "used": []
  },
  {
    "text": "Box of turquoise animal figurines",
    "unique": false,
    "used": []
  },
  {
    "text": "Brass mug with jade inlay",
    "unique": false,
    "used": []
  },
  {
    "text": "Bronze crown",
    "unique": false,
    "used": []
  },
  {
    "text": "Bronze spyglass (Brazen Coalition)",
    "unique": false,
    "used": []
  },
  {
    "text": "Bundle of sheet music representing the lost dirges of a famous composer",
    "unique": false,
    "used": []
  },
  {
    "text": "Carved bone statuette",
    "unique": false,
    "used": []
  },
  {
    "text": "Carved ivory statuette",
    "unique": false,
    "used": []
  },
  {
    "text": "Carved jade statuette (River Heralds)",
    "unique": false,
    "used": []
  },
  {
    "text": "Carved wooden harp with ivory inlay and zircon gems",
    "unique": false,
    "used": []
  },
  {
    "text": "Ceremonial gold armor with black pearls",
    "unique": false,
    "used": []
  },
  {
    "text": "Ceremonial silver dagger with gold pommel and black pearl (Legion of Dusk)",
    "unique": false,
    "used": []
  },
  {
    "text": "Cloth-of-gold vestments",
    "unique": false,
    "used": []
  },
  {
    "text": "Cloth-of-gold vestments (Legion of Dusk)",
    "unique": false,
    "used": []
  },
  {
    "text": "Copper chalice with silver filigree",
    "unique": false,
    "used": []
  },
  {
    "text": "Copper stein with silver filigree (Brazen Coalition)",
    "unique": false,
    "used": []
  },
  {
    "text": "Detailed, life-sized dragonborn skull cast in electrum",
    "unique": false,
    "used": []
  },
  {
    "text": "Embroidered glove set with jewel chips",
    "unique": false,
    "used": []
  },
  {
    "text": "Embroidered silk and velvet mantle set with numerous moonstones",
    "unique": false,
    "used": []
  },
  {
    "text": "Embroidered silk handkerchief",
    "unique": false,
    "used": []
  },
  {
    "text": "Eye patch decorated with tiny blue sapphires and moonstones",
    "unique": false,
    "used": []
  },
  {
    "text": "Eye patch with a mock eye set in blue sapphire and moonstone (Brazen Coalition)",
    "unique": false,
    "used": []
  },
  {
    "text": "Feathered mantle with emerald clasp (Sun Empire)",
    "unique": false,
    "used": []
  },
  {
    "text": "Fine gold chain set with a fire opal",
    "unique": false,
    "used": []
  },
  {
    "text": "Fine gold chain with fire opals (Legion of Dusk)",
    "unique": false,
    "used": []
  },
  {
    "text": "Fine robe with dinosaur feathers and silver embroidery (Sun Empire)",
    "unique": false,
    "used": []
  },
  {
    "text": "Fine steel rapier with gold filigree hilt (Legion of Dusk)",
    "unique": false,
    "used": []
  },
  {
    "text": "Finely articulated jade glove (River Heralds)",
    "unique": false,
    "used": []
  },
  {
    "text": "Gilded royal coach or funeral barge",
    "unique": false,
    "used": []
  },
  {
    "text": "Gold basin with rubies (Legion of Dusk)",
    "unique": false,
    "used": []
  },
  {
    "text": "Gold birdcage with electrum filigree",
    "unique": false,
    "used": []
  },
  {
    "text": "Gold bracelet",
    "unique": false,
    "used": []
  },
  {
    "text": "Gold chalice (Legion of Dusk)",
    "unique": false,
    "used": []
  },
  {
    "text": "Gold chalice set with emeralds (Legion of Dusk)",
    "unique": false,
    "used": []
  },
  {
    "text": "Gold circlet set with four aquamarines",
    "unique": false,
    "used": []
  },
  {
    "text": "Gold comb shaped like a dragon with red garnets as eyes",
    "unique": false,
    "used": []
  },
  {
    "text": "Gold cup set with emeralds",
    "unique": false,
    "used": []
  },
  {
    "text": "Gold idol",
    "unique": false,
    "used": []
  },
  {
    "text": "Gold jewelry box with platinum filigree",
    "unique": false,
    "used": []
  },
  {
    "text": "Gold jewelry box with platinum filigree (Brazen Coalition)",
    "unique": false,
    "used": []
  },
  {
    "text": "Gold locket with a painted portrait inside",
    "unique": false,
    "used": []
  },
  {
    "text": "Gold locket with a painted portrait inside (Legion of Dusk)",
    "unique": false,
    "used": []
  },
  {
    "text": "Gold music box",
    "unique": false,
    "used": []
  },
  {
    "text": "Gold music box (Brazen Coalition)",
    "unique": false,
    "used": []
  },
  {
    "text": "Gold pendant with black onyx (Legion of Dusk)",
    "unique": false,
    "used": []
  },
  {
    "text": "Gold ring set with bloodstones",
    "unique": false,
    "used": []
  },
  {
    "text": "Gold ring with turquoise (Legion of Dusk)",
    "unique": false,
    "used": []
  },
  {
    "text": "Gold statuette set with rubies",
    "unique": false,
    "used": []
  },
  {
    "text": "Gold-plated ceremonial helmet and pauldrons (Legion of Dusk)",
    "unique": false,
    "used": []
  },
  {
    "text": "Gold-plated sextant with topaz (Brazen Coalition)",
    "unique": false,
    "used": []
  },
  {
    "text": "Handheld mirror set in a painted wooden frame",
    "unique": false,
    "used": []
  },
  {
    "text": "Jade bowl (River Heralds)",
    "unique": false,
    "used": []
  },
  {
    "text": "Jade breastplate (River Heralds)",
    "unique": false,
    "used": []
  },
  {
    "text": "Jade game board with gold playing pieces",
    "unique": false,
    "used": []
  },
  {
    "text": "Jade headpiece (River Heralds)",
    "unique": false,
    "used": []
  },
  {
    "text": "Jade sword with amber (River Heralds)",
    "unique": false,
    "used": []
  },
  {
    "text": "Jade totem with diamond eyes (River Heralds)",
    "unique": false,
    "used": []
  },
  {
    "text": "Jeweled anklet",
    "unique": false,
    "used": []
  },
  {
    "text": "Jeweled anklet (Brazen Coalition)",
    "unique": false,
    "used": []
  },
  {
    "text": "Jeweled gold crown",
    "unique": false,
    "used": []
  },
  {
    "text": "Jeweled platinum ring",
    "unique": false,
    "used": []
  },
  {
    "text": "Large gold bracelet (Legion of Dusk)",
    "unique": false,
    "used": []
  },
  {
    "text": "Large jade totem (River Heralds)",
    "unique": false,
    "used": []
  },
  {
    "text": "Large well-made tapestry (Legion of Dusk)",
    "unique": false,
    "used": []
  },
  {
    "text": "Lute crafted of exotic wood with mother-of-pearl inlay and zircon gems (Brazen Coalition)",
    "unique": false,
    "used": []
  },
  {
    "text": "Marble font with gold inlay (Legion of Dusk)",
    "unique": false,
    "used": []
  },
  {
    "text": "Masterpiece painting in mahogany frame with gold inlay (Legion of Dusk)",
    "unique": false,
    "used": []
  },
  {
    "text": "Necklace of electrum medallions with red and blue tourmalines (Brazen Coalition)",
    "unique": false,
    "used": []
  },
  {
    "text": "Necklace of jade and pink pearls (River Heralds)",
    "unique": false,
    "used": []
  },
  {
    "text": "Necklace string of small pink pearls",
    "unique": false,
    "used": []
  },
  {
    "text": "Obsidian statuette with gold fittings and inlay",
    "unique": false,
    "used": []
  },
  {
    "text": "Old masterpiece painting",
    "unique": false,
    "used": []
  },
  {
    "text": "Painted gold war mask",
    "unique": false,
    "used": []
  },
  {
    "text": "Pair of engraved bone dice",
    "unique": false,
    "used": []
  },
  {
    "text": "Pair of engraved bone dice (Brazen Coalition)",
    "unique": false,
    "used": []
  },
  {
    "text": "Pewter mug with green spinels (Brazen Coalition)",
    "unique": false,
    "used": []
  },
  {
    "text": "Platinum bracelet set with an emerald",
    "unique": false,
    "used": []
  },
  {
    "text": "Platinum headdress with topaz sun symbol (Sun Empire)",
    "unique": false,
    "used": []
  },
  {
    "text": "Platinum ring with yellow sapphire (Sun Empire)",
    "unique": false,
    "used": []
  },
  {
    "text": "Platinum staff topped with amber (Sun Empire)",
    "unique": false,
    "used": []
  },
  {
    "text": "Set of gold nesting dolls",
    "unique": false,
    "used": []
  },
  {
    "text": "Silk vestments with gold embroidery",
    "unique": false,
    "used": []
  },
  {
    "text": "Silver and gold brooch",
    "unique": false,
    "used": []
  },
  {
    "text": "Silver chalice set with moonstones",
    "unique": false,
    "used": []
  },
  {
    "text": "Silver ewer",
    "unique": false,
    "used": []
  },
  {
    "text": "Silver headdress with amber and red-coral feathers (Sun Empire)",
    "unique": false,
    "used": []
  },
  {
    "text": "Silver medallion (Sun Empire)",
    "unique": false,
    "used": []
  },
  {
    "text": "Silver necklace with a gemstone pendant",
    "unique": false,
    "used": []
  },
  {
    "text": "Silver necklace with an amber pendant (Sun Empire)",
    "unique": false,
    "used": []
  },
  {
    "text": "Silver shoulder piece with amber and garnet (Sun Empire)",
    "unique": false,
    "used": []
  },
  {
    "text": "Sun amulet on a beaded chain (Sun Empire)",
    "unique": false,
    "used": []
  },
  {
    "text": "Tiny jade figurine (River Heralds)",
    "unique": false,
    "used": []
  },
  {
    "text": "Treasure chest crafted of exotic wood with gold fittings and opals (Brazen Coalition)",
    "unique": false,
    "used": []
  },
  {
    "text": "Velvet doublet with gold buttons (Legion of Dusk)",
    "unique": false,
    "used": []
  },
  {
    "text": "Well-made tapestry that is 10 feet by 10 feet",
    "unique": false,
    "used": []
  }
]